openmm/lib/OpenMMTorch.dll
openmm/lib/OpenMMTorch.lib
openmm/lib/plugins/OpenMMTorchCUDA.dll
openmm/lib/plugins/OpenMMTorchCUDA.lib
openmm/lib/plugins/OpenMMTorchOpenCL.dll
openmm/lib/plugins/OpenMMTorchOpenCL.lib
openmm/lib/plugins/OpenMMTorchReference.dll
openmm/lib/plugins/OpenMMTorchReference.lib
openmmtorch/TorchPluginWrapper.cpp
openmmtorch/__init__.py
openmmtorch/_openmmtorch.cp310-win_amd64.pyd
openmmtorch/openmmtorch.py
openmmtorch/include/TorchForce.h
openmmtorch/include/TorchKernels.h
openmmtorch/include/internal/TorchForceImpl.h
openmmtorch/include/internal/windowsExportTorch.h
openmm_torch_unofficial_cu12-1.5.dist-info/METADATA
openmm_torch_unofficial_cu12-1.5.dist-info/WHEEL
openmm_torch_unofficial_cu12-1.5.dist-info/top_level.txt
openmm_torch_unofficial_cu12-1.5.dist-info/RECORD
