Metadata-Version: 2.4
Name: openmm-torch-unofficial-cu12
Version: 1.5
Summary: Python wrapper for OpenMM (a C++ MD package)
Author-email: Peter Eastman <peastman@stanford.edu>
License-Expression: PSF-2.0
Project-URL: Homepage, https://openmm.org
Project-URL: Bug Tracker, https://github.com/openmm/openmm/issues
Project-URL: Download URL, https://openmm.org
Classifier: Programming Language :: Python :: 3
Requires-Python: >=3.8
Requires-Dist: nvidia-cuda-runtime-cu12
Dynamic: requires-dist
